{"updated":"2026-07-20","session":"2026-07-20","sessions_collected":7,"caveat":"Block/negotiated-market feed is ~1 session lagged with no historical archive \u2014 accumulating daily. The cross-market flag is EXPERIMENTAL (single-session, not yet backtested for false-positive rate); it hardens once \u226520 sessions are collected. Descriptive pattern only \u2014 never proof of manipulation.","tickers":{"AAMRATECH":{"value_mn":2.77,"trades":1,"vol":175000,"price":"15.8\u201315.8","date":"2026-07-20","ratio":0.71,"vr":0.35,"smart_flow":1.04,"flag":"","note":"Block trade \u09f32.8M (1 trade), 0.3\u00d7 normal public volume, institutional ownership +1.0pp."},"ALLTEX":{"value_mn":0.5,"trades":1,"vol":28600,"price":"17.6\u201317.6","date":"2026-07-20","ratio":0.07,"vr":0.89,"smart_flow":0.25,"flag":"","note":"Block trade \u09f30.5M (1 trade), 0.9\u00d7 normal public volume, institutional ownership +0.2pp."},"ASIAPACINS":{"value_mn":0.59,"trades":1,"vol":11999,"price":"49.5\u201349.5","date":"2026-07-20","ratio":0.04,"vr":1.56,"smart_flow":2.42,"flag":"","note":"Block trade \u09f30.6M (1 trade), 1.6\u00d7 normal public volume, institutional ownership +2.4pp."},"BNICL":{"value_mn":12.36,"trades":3,"vol":104800,"price":"115.7\u2013121.5","date":"2026-07-20","ratio":0.22,"vr":0.35,"smart_flow":-0.83,"flag":"","note":"Block trade \u09f312.4M (3 trades), 0.3\u00d7 normal public volume, institutional ownership -0.8pp."},"BSRMSTEEL":{"value_mn":14.17,"trades":2,"vol":140000,"price":"99.8\u2013102","date":"2026-07-20","ratio":0.14,"vr":0.89,"smart_flow":-0.1,"flag":"","note":"Block trade \u09f314.2M (2 trades), 0.9\u00d7 normal public volume, institutional ownership -0.1pp."},"CAPMIBBLMF":{"value_mn":2.28,"trades":1,"vol":149788,"price":"15.2\u201315.2","date":"2026-07-20","ratio":0.16,"vr":0.84,"smart_flow":-1.03,"flag":"","note":"Block trade \u09f32.3M (1 trade), 0.8\u00d7 normal public volume, institutional ownership -1.0pp."},"CITYBANK":{"value_mn":38.55,"trades":3,"vol":1350000,"price":"28.4\u201328.8","date":"2026-07-20","ratio":0.24,"vr":0.69,"smart_flow":9.64,"flag":"","note":"Block trade \u09f338.5M (3 trades), 0.7\u00d7 normal public volume, institutional ownership +9.6pp."},"DAFODILCOM":{"value_mn":7.83,"trades":5,"vol":49697,"price":"157\u2013158","date":"2026-07-20","ratio":0.14,"vr":0.34,"smart_flow":1.23,"flag":"","note":"Block trade \u09f37.8M (5 trades), 0.3\u00d7 normal public volume, institutional ownership +1.2pp."},"DBH":{"value_mn":6.42,"trades":3,"vol":142676,"price":"45\u201345","date":"2026-07-20","ratio":0.38,"vr":1.11,"smart_flow":0.16,"flag":"","note":"Block trade \u09f36.4M (3 trades), 1.1\u00d7 normal public volume, institutional ownership +0.2pp."},"EHL":{"value_mn":0.79,"trades":1,"vol":8200,"price":"96.3\u201396.3","date":"2026-07-20","ratio":0.01,"vr":0.56,"smart_flow":0.76,"flag":"","note":"Block trade \u09f30.8M (1 trade), 0.6\u00d7 normal public volume, institutional ownership +0.8pp."},"EPGL":{"value_mn":0.69,"trades":1,"vol":31500,"price":"21.8\u201321.8","date":"2026-07-20","ratio":0.04,"vr":0.31,"smart_flow":0.03,"flag":"","note":"Block trade \u09f30.7M (1 trade), 0.3\u00d7 normal public volume, institutional ownership +0.0pp."},"FEKDIL":{"value_mn":4.99,"trades":1,"vol":198000,"price":"25.2\u201325.2","date":"2026-07-20","ratio":0.04,"vr":1.43,"smart_flow":8.67,"flag":"","note":"Block trade \u09f35.0M (1 trade), 1.4\u00d7 normal public volume, institutional ownership +8.7pp."},"IBP":{"value_mn":0.62,"trades":1,"vol":31000,"price":"20.1\u201320.1","date":"2026-07-20","ratio":0.01,"vr":0.49,"smart_flow":10.06,"flag":"","note":"Block trade \u09f30.6M (1 trade), 0.5\u00d7 normal public volume, institutional ownership +10.1pp."},"ITC":{"value_mn":0.51,"trades":1,"vol":10100,"price":"50\u201350","date":"2026-07-20","ratio":0.0,"vr":0.55,"smart_flow":-4.94,"flag":"","note":"Block trade \u09f30.5M (1 trade), 0.6\u00d7 normal public volume, institutional ownership -4.9pp."},"LHB":{"value_mn":3.78,"trades":1,"vol":57066,"price":"66.2\u201366.2","date":"2026-07-20","ratio":0.03,"vr":1.21,"smart_flow":0.29,"flag":"","note":"Block trade \u09f33.8M (1 trade), 1.2\u00d7 normal public volume, institutional ownership +0.3pp."},"LOVELLO":{"value_mn":12.28,"trades":2,"vol":162000,"price":"73.2\u201376","date":"2026-07-20","ratio":0.07,"vr":0.74,"smart_flow":-1.59,"flag":"","note":"Block trade \u09f312.3M (2 trades), 0.7\u00d7 normal public volume, institutional ownership -1.6pp."},"MALEKSPIN":{"value_mn":0.88,"trades":1,"vol":20000,"price":"44.2\u201344.2","date":"2026-07-20","ratio":0.0,"vr":1.52,"smart_flow":9.28,"flag":"accumulation","note":"Block trade \u09f30.9M (1 trade), 1.5\u00d7 normal public volume, institutional ownership +9.3pp \u2014 consistent with cross-venue accumulation this session. Pattern, not proof."},"MEGHNAINS":{"value_mn":5.25,"trades":2,"vol":130000,"price":"40\u201341.5","date":"2026-07-20","ratio":0.06,"vr":1.21,"smart_flow":-0.89,"flag":"","note":"Block trade \u09f35.2M (2 trades), 1.2\u00d7 normal public volume, institutional ownership -0.9pp."},"MEGHNAPET":{"value_mn":6.66,"trades":5,"vol":77422,"price":"86\u201386","date":"2026-07-20","ratio":0.46,"vr":1.6,"smart_flow":0.0,"flag":"","note":"Block trade \u09f36.7M (5 trades), 1.6\u00d7 normal public volume, institutional ownership +0.0pp."},"MIRAKHTER":{"value_mn":0.63,"trades":1,"vol":16700,"price":"37.8\u201337.8","date":"2026-07-20","ratio":0.02,"vr":2.94,"smart_flow":-5.23,"flag":"distribution","note":"Block trade \u09f30.6M (1 trade), 2.9\u00d7 normal public volume, institutional ownership -5.2pp \u2014 consistent with cross-venue distribution this session. Pattern, not proof."},"NITOLINS":{"value_mn":3.32,"trades":2,"vol":86500,"price":"38.4\u201338.4","date":"2026-07-20","ratio":0.42,"vr":0.62,"smart_flow":-0.74,"flag":"","note":"Block trade \u09f33.3M (2 trades), 0.6\u00d7 normal public volume, institutional ownership -0.7pp."},"ORIONINFU":{"value_mn":16.0,"trades":1,"vol":50000,"price":"320\u2013320","date":"2026-07-20","ratio":0.27,"vr":0.9,"smart_flow":-0.25,"flag":"","note":"Block trade \u09f316.0M (1 trade), 0.9\u00d7 normal public volume, institutional ownership -0.2pp."},"PEOPLESINS":{"value_mn":3.1,"trades":1,"vol":50000,"price":"62\u201362","date":"2026-07-20","ratio":0.04,"vr":0.47,"smart_flow":-1.06,"flag":"","note":"Block trade \u09f33.1M (1 trade), 0.5\u00d7 normal public volume, institutional ownership -1.1pp."},"PREMIERBAN":{"value_mn":1.59,"trades":1,"vol":317125,"price":"5\u20135","date":"2026-07-20","ratio":0.37,"vr":1.22,"smart_flow":0.32,"flag":"","note":"Block trade \u09f31.6M (1 trade), 1.2\u00d7 normal public volume, institutional ownership +0.3pp."},"PROVATIINS":{"value_mn":1.9,"trades":1,"vol":28500,"price":"66.8\u201366.8","date":"2026-07-20","ratio":0.03,"vr":0.55,"smart_flow":-4.64,"flag":"","note":"Block trade \u09f31.9M (1 trade), 0.5\u00d7 normal public volume, institutional ownership -4.6pp."},"RUNNERAUTO":{"value_mn":0.59,"trades":1,"vol":13500,"price":"44.1\u201344.1","date":"2026-07-20","ratio":0.01,"vr":0.3,"smart_flow":0.49,"flag":"","note":"Block trade \u09f30.6M (1 trade), 0.3\u00d7 normal public volume, institutional ownership +0.5pp."},"SHARPIND":{"value_mn":14.05,"trades":2,"vol":418977,"price":"30.2\u201336.6","date":"2026-07-20","ratio":0.19,"vr":1.24,"smart_flow":0.37,"flag":"","note":"Block trade \u09f314.1M (2 trades), 1.2\u00d7 normal public volume, institutional ownership +0.4pp."},"SICL":{"value_mn":2.01,"trades":1,"vol":48000,"price":"41.9\u201341.9","date":"2026-07-20","ratio":0.04,"vr":0.47,"smart_flow":0.57,"flag":"","note":"Block trade \u09f32.0M (1 trade), 0.5\u00d7 normal public volume, institutional ownership +0.6pp."},"SPCERAMICS":{"value_mn":0.51,"trades":1,"vol":19700,"price":"25.8\u201325.8","date":"2026-07-20","ratio":0.01,"vr":0.37,"smart_flow":-0.15,"flag":"","note":"Block trade \u09f30.5M (1 trade), 0.4\u00d7 normal public volume, institutional ownership -0.1pp."},"SPCL":{"value_mn":0.58,"trades":1,"vol":10000,"price":"58.4\u201358.4","date":"2026-07-20","ratio":0.01,"vr":0.52,"smart_flow":1.09,"flag":"","note":"Block trade \u09f30.6M (1 trade), 0.5\u00d7 normal public volume, institutional ownership +1.1pp."},"STANDARINS":{"value_mn":4.13,"trades":1,"vol":76500,"price":"54\u201354","date":"2026-07-20","ratio":0.18,"vr":0.48,"smart_flow":1.5,"flag":"","note":"Block trade \u09f34.1M (1 trade), 0.5\u00d7 normal public volume, institutional ownership +1.5pp."},"SUNLIFEINS":{"value_mn":1.1,"trades":1,"vol":15400,"price":"71.5\u201371.5","date":"2026-07-20","ratio":0.02,"vr":0.55,"smart_flow":-9.19,"flag":"","note":"Block trade \u09f31.1M (1 trade), 0.6\u00d7 normal public volume, institutional ownership -9.2pp."},"TAKAFULINS":{"value_mn":11.95,"trades":1,"vol":219234,"price":"54.5\u201354.5","date":"2026-07-20","ratio":1.18,"vr":0.99,"smart_flow":1.72,"flag":"","note":"Block trade \u09f311.9M (1 trade), 1.0\u00d7 normal public volume, institutional ownership +1.7pp."},"TECHNODRUG":{"value_mn":1.81,"trades":2,"vol":38000,"price":"47.1\u201348","date":"2026-07-20","ratio":0.03,"vr":5.37,"smart_flow":-3.15,"flag":"distribution","note":"Block trade \u09f31.8M (2 trades), 5.4\u00d7 normal public volume, institutional ownership -3.1pp \u2014 consistent with cross-venue distribution this session. Pattern, not proof."}}}