{"updated":"2026-07-11","generated":"2026-07-12 13:25","session":"intraday","live":true,"src":"dse_ohlcv_rolling.csv.gz","tiers":{"core":[{"s":"MTB","t":"core","e":"fair","p":7,"sc":79,"fv":"SUSTAINABLE","cat":"A","rsi":49,"macd":"bull","vol":0.7,"ch":"Double Bottom","cd":"Three Outside Up","px":14.0,"sup":"13.2","res":"14.7","stop":"close<12.8 (buffer)","tgt":"ride/trail; ref 16.7","f":"Double Bottom \u00b7 >50MA \u00b7 uptrend \u00b7 MACD bull \u00b7 RSI 49"},{"s":"CITYBANK","t":"core","e":"IN-ZONE","p":4,"sc":76,"fv":"SUSTAINABLE","cat":"A","rsi":52,"macd":"bear","vol":0.5,"ch":"","cd":"","px":30.7,"sup":"28.9","res":"31.7","stop":"close<29.6 (buffer)","tgt":"ride/trail; ref 37.1","f":">50MA \u00b7 uptrend \u00b7 MACD bear \u00b7 RSI 52"},{"s":"DHAKABANK","t":"core","e":"IN-ZONE","p":4,"sc":77,"fv":"SUSTAINABLE","cat":"A","rsi":54,"macd":"bear","vol":0.3,"ch":"","cd":"","px":12.1,"sup":"12.0","res":"12.6","stop":"close<11.7 (buffer)","tgt":"ride/trail; ref 13.5","f":">50MA \u00b7 uptrend \u00b7 MACD bear \u00b7 RSI 54"},{"s":"SQURPHARMA","t":"core","e":"fair","p":4,"sc":85,"fv":"SUSTAINABLE","cat":"A","rsi":61,"macd":"bear","vol":0.4,"ch":"","cd":"Bullish Harami","px":221.4,"sup":"213.0","res":"228.0","stop":"close<213.6 (buffer)","tgt":"ride/trail; ref 255.2","f":">50MA \u00b7 uptrend \u00b7 MACD bear \u00b7 RSI 61"},{"s":"MPETROLEUM","t":"core","e":"fair","p":4,"sc":83,"fv":"SUSTAINABLE","cat":"A","rsi":67,"macd":"bull","vol":0.3,"ch":"","cd":"Bullish Engulfing","px":215.2,"sup":"204.2","res":"217.5","stop":"close<205.3 (buffer)","tgt":"ride/trail; ref 249.4","f":">50MA \u00b7 uptrend \u00b7 MACD bull \u00b7 RSI 67"},{"s":"BRACBANK","t":"core","e":"IN-ZONE","p":3,"sc":74,"fv":"SUSTAINABLE","cat":"A","rsi":33,"macd":"bear","vol":0.4,"ch":"","cd":"Morning Star","px":62.5,"sup":"60.8","res":"65.2","stop":"close<63.7 (buffer)","tgt":"ride/trail; ref 61.8","f":"candle +1.52% \u00b7 uptrend \u00b7 MACD bear \u00b7 RSI 33"},{"s":"BERGERPBL","t":"core","e":"IN-ZONE","p":2,"sc":73,"fv":"SUSTAINABLE","cat":"A","rsi":37,"macd":"bear","vol":0.7,"ch":"","cd":"Bullish Engulfing","px":1394.3,"sup":"1386.0","res":"1445.0","stop":"close<1374.4 (buffer)","tgt":"ride/trail; ref 1526.4","f":"candle +0.25% \u00b7 MACD bear \u00b7 RSI 37"},{"s":"JAMUNABANK","t":"core","e":"IN-ZONE","p":2,"sc":77,"fv":"SUSTAINABLE","cat":"A","rsi":44,"macd":"bear","vol":0.5,"ch":"","cd":"","px":23.6,"sup":"23.3","res":"26.4","stop":"close<23.2 (buffer)","tgt":"ride/trail; ref 24.1","f":"uptrend \u00b7 MACD bear \u00b7 RSI 44"},{"s":"EBL","t":"core","e":"IN-ZONE","p":2,"sc":80,"fv":"SUSTAINABLE","cat":"","rsi":44,"macd":"bear","vol":0.4,"ch":"","cd":"","px":24.6,"sup":"24.2","res":"25.4","stop":"close<24.1 (buffer)","tgt":"ride/trail; ref 25.9","f":"uptrend \u00b7 MACD bear \u00b7 RSI 44"},{"s":"MARICO","t":"core","e":"IN-ZONE","p":2,"sc":87,"fv":"SUSTAINABLE","cat":"A","rsi":45,"macd":"bear","vol":0.4,"ch":"","cd":"","px":2732.0,"sup":"2720.0","res":"2793.0","stop":"close<2671.6 (buffer)","tgt":"ride/trail; ref 2967.3","f":"MACD bear \u00b7 RSI 45"},{"s":"SHAHJABANK","t":"core","e":"fair","p":2,"sc":82,"fv":"SUSTAINABLE","cat":"A","rsi":69,"macd":"bear","vol":0.2,"ch":"","cd":"","px":17.5,"sup":"16.7","res":"17.8","stop":"close<16.8 (buffer)","tgt":"ride/trail; ref 20.5","f":">50MA \u00b7 MACD bear \u00b7 RSI 69"}],"hot":[{"s":"IDLC","t":"core","e":"EXTENDED","p":9,"sc":80,"fv":"SUSTAINABLE","cat":"A","rsi":78,"macd":"bull","vol":1.8,"ch":"Double Bottom","cd":"Three Outside Up","px":44.1,"sup":"40.5","res":"","stop":"close<40.0 (buffer)","tgt":"ride/trail; ref 53.4","f":"Double Bottom \u00b7 candle +1.05% \u00b7 >50MA \u00b7 uptrend \u00b7 20d-breakout \u00b7 vol 1.8x \u00b7 MACD bull \u00b7 RSI 78"},{"s":"UNIQUEHRL","t":"core","e":"EXTENDED","p":7,"sc":73,"fv":"SUSTAINABLE","cat":"A","rsi":78,"macd":"bull","vol":1.7,"ch":"Double Bottom","cd":"","px":48.2,"sup":"39.8","res":"49.8","stop":"close<40.4 (buffer)","tgt":"ride/trail; ref 70.6","f":"Double Bottom \u00b7 >50MA \u00b7 uptrend \u00b7 vol 1.7x \u00b7 MACD bull \u00b7 RSI 78"},{"s":"CONFIDCEM","t":"core","e":"EXTENDED","p":6,"sc":78,"fv":"SUSTAINABLE","cat":"A","rsi":79,"macd":"bull","vol":2.1,"ch":"","cd":"","px":71.3,"sup":"62.6","res":"","stop":"close<63.2 (buffer)","tgt":"ride/trail; ref 87.4","f":">50MA \u00b7 uptrend \u00b7 20d-breakout \u00b7 vol 2.1x \u00b7 MACD bull \u00b7 RSI 79"},{"s":"ITC","t":"core","e":"EXTENDED","p":6,"sc":81,"fv":"SUSTAINABLE","cat":"A","rsi":94,"macd":"bull","vol":1.1,"ch":"","cd":"Three Outside Up","px":52.5,"sup":"40.8","res":"","stop":"close<43.1 (buffer)","tgt":"ride/trail; ref 78.0","f":"candle \u00b7 >50MA \u00b7 uptrend \u00b7 20d-breakout \u00b7 MACD bull \u00b7 RSI 94"},{"s":"DBH","t":"core","e":"EXTENDED","p":6,"sc":75,"fv":"SUSTAINABLE","cat":"A","rsi":60,"macd":"bull","vol":0.9,"ch":"","cd":"Three Inside Up","px":42.7,"sup":"38.3","res":"42.8","stop":"close<39.4 (buffer)","tgt":"ride/trail; ref 48.9","f":"candle \u00b7 >50MA \u00b7 uptrend \u00b7 MACD bull \u00b7 RSI 60"},{"s":"MJLBD","t":"core","e":"EXTENDED","p":6,"sc":79,"fv":"SUSTAINABLE","cat":"A","rsi":76,"macd":"bull","vol":0.9,"ch":"Double Bottom","cd":"","px":96.5,"sup":"89.0","res":"","stop":"close<89.7 (buffer)","tgt":"ride/trail; ref 114.2","f":"Double Bottom \u00b7 >50MA \u00b7 20d-breakout \u00b7 MACD bull \u00b7 RSI 76"},{"s":"ACMELAB","t":"core","e":"EXTENDED","p":5,"sc":80,"fv":"SUSTAINABLE","cat":"A","rsi":82,"macd":"bull","vol":1.1,"ch":"","cd":"","px":85.7,"sup":"78.4","res":"","stop":"close<78.7 (buffer)","tgt":"ride/trail; ref 104.7","f":">50MA \u00b7 uptrend \u00b7 20d-breakout \u00b7 MACD bull \u00b7 RSI 82"},{"s":"IBNSINA","t":"core","e":"EXTENDED","p":5,"sc":87,"fv":"SUSTAINABLE","cat":"A","rsi":83,"macd":"bull","vol":1.0,"ch":"","cd":"Inverted Hammer","px":322.6,"sup":"306.0","res":"328.6","stop":"close<307.1 (buffer)","tgt":"ride/trail; ref 367.6","f":"candle +0.82% \u00b7 >50MA \u00b7 20d-breakout \u00b7 MACD bull \u00b7 RSI 83"}],"caution":[{"s":"NCCBLMF1","t":"caution","e":"EXTENDED","p":8,"sc":55,"fv":"WATCH","cat":"A","rsi":74,"macd":"bull","vol":4.2,"ch":"Double Bottom","cd":"Bullish Engulfing","px":5.3,"sup":"4.8","res":"","stop":"close<4.3 (buffer)","tgt":"ride/trail; ref 6.5","f":"Double Bottom \u00b7 candle \u00b7 >50MA \u00b7 uptrend \u00b7 20d-breakout \u00b7 vol 4.2x \u00b7 MACD bull \u00b7 RSI 74"},{"s":"RUPALIINS","t":"caution","e":"EXTENDED","p":8,"sc":30,"fv":"WATCH","cat":"A","rsi":73,"macd":"bull","vol":2.3,"ch":"Double Bottom","cd":"Three Outside Up","px":30.7,"sup":"27.3","res":"","stop":"n/a","tgt":"\u2014","f":"Double Bottom \u00b7 candle +0.89% \u00b7 >50MA \u00b7 uptrend \u00b7 20d-breakout \u00b7 vol 2.3x \u00b7 MACD bull \u00b7 RSI 73"},{"s":"EASTLAND","t":"caution","e":"EXTENDED","p":7,"sc":30,"fv":"WATCH","cat":"A","rsi":80,"macd":"bull","vol":2.8,"ch":"Double Bottom","cd":"Three Outside Up","px":30.3,"sup":"25.4","res":"","stop":"n/a","tgt":"\u2014","f":"Double Bottom \u00b7 >50MA \u00b7 uptrend \u00b7 20d-breakout \u00b7 vol 2.8x \u00b7 MACD bull \u00b7 RSI 80"},{"s":"CENTRALINS","t":"caution","e":"EXTENDED","p":7,"sc":36,"fv":"WATCH","cat":"A","rsi":58,"macd":"bull","vol":2.6,"ch":"","cd":"Three Outside Up","px":45.1,"sup":"42.1","res":"","stop":"n/a","tgt":"\u2014","f":"candle +0.63% \u00b7 >50MA \u00b7 uptrend \u00b7 20d-breakout \u00b7 vol 2.6x \u00b7 MACD bull \u00b7 RSI 58"},{"s":"SPCL","t":"caution","e":"EXTENDED","p":7,"sc":35,"fv":"WATCH","cat":"A","rsi":75,"macd":"bull","vol":1.4,"ch":"Double Bottom","cd":"Three Outside Up","px":59.0,"sup":"54.1","res":"59.2","stop":"n/a","tgt":"\u2014","f":"Double Bottom \u00b7 candle \u00b7 >50MA \u00b7 uptrend \u00b7 vol 1.4x \u00b7 MACD bull \u00b7 RSI 75"},{"s":"JANATAINS","t":"caution","e":"IN-ZONE","p":6,"sc":14,"fv":"WATCH","cat":"A","rsi":58,"macd":"bull","vol":2.2,"ch":"","cd":"Three Outside Up","px":37.0,"sup":"36.1","res":"37.7","stop":"if held: EXIT now / close<35.4","tgt":"\u2014","f":"candle \u00b7 >50MA \u00b7 uptrend \u00b7 vol 2.2x \u00b7 MACD bull \u00b7 RSI 58"},{"s":"EASTERNINS","t":"caution","e":"IN-ZONE","p":6,"sc":32,"fv":"WATCH","cat":"A","rsi":50,"macd":"bull","vol":1.4,"ch":"","cd":"Three Outside Up","px":61.6,"sup":"61.3","res":"63.2","stop":"n/a","tgt":"\u2014","f":"candle +3.5% \u00b7 >50MA \u00b7 uptrend \u00b7 vol 1.4x \u00b7 MACD bull \u00b7 RSI 50"},{"s":"LOVELLO","t":"caution","e":"EXTENDED","p":6,"sc":15,"fv":"WATCH","cat":"A","rsi":66,"macd":"bull","vol":4.8,"ch":"","cd":"Bullish Engulfing","px":76.2,"sup":"67.5","res":"","stop":"if held: EXIT now / close<71.1","tgt":"\u2014","f":"candle \u00b7 >50MA \u00b7 20d-breakout \u00b7 vol 4.8x \u00b7 MACD bull \u00b7 RSI 66"},{"s":"MEGHNALIFE","t":"caution","e":"EXTENDED","p":6,"sc":40,"fv":"WATCH","cat":"A","rsi":65,"macd":"bull","vol":4.0,"ch":"","cd":"Three Outside Up","px":65.6,"sup":"57.4","res":"","stop":"n/a","tgt":"\u2014","f":">50MA \u00b7 uptrend \u00b7 20d-breakout \u00b7 vol 4.0x \u00b7 MACD bull \u00b7 RSI 65"},{"s":"POPULARLIF","t":"caution","e":"EXTENDED","p":6,"sc":53,"fv":"WATCH","cat":"A","rsi":61,"macd":"bull","vol":2.7,"ch":"","cd":"Three Outside Up","px":66.1,"sup":"62.8","res":"66.3","stop":"close<60.0 (buffer)","tgt":"ride/trail; ref 79.9","f":"candle \u00b7 >50MA \u00b7 uptrend \u00b7 vol 2.7x \u00b7 MACD bull \u00b7 RSI 61"}],"risk":[{"s":"EXIM1STMF","t":"risk","e":"EXTENDED","p":9,"sc":8,"fv":"AT-RISK","cat":"A","rsi":64,"macd":"bull","vol":5.2,"ch":"Double Bottom","cd":"Bullish Engulfing","px":3.9,"sup":"3.8","res":"4.0","stop":"n/a","tgt":"\u2014","f":"Double Bottom \u00b7 candle \u00b7 >50MA \u00b7 uptrend \u00b7 20d-breakout \u00b7 vol 5.2x \u00b7 MACD bull \u00b7 RSI 64"},{"s":"FBFIF","t":"risk","e":"EXTENDED","p":9,"sc":8,"fv":"AT-RISK","cat":"A","rsi":64,"macd":"bull","vol":2.8,"ch":"Double Bottom","cd":"Bullish Engulfing","px":3.4,"sup":"3.2","res":"3.5","stop":"n/a","tgt":"\u2014","f":"Double Bottom \u00b7 candle \u00b7 >50MA \u00b7 uptrend \u00b7 20d-breakout \u00b7 vol 2.8x \u00b7 MACD bull \u00b7 RSI 64"},{"s":"EBL1STMF","t":"risk","e":"EXTENDED","p":8,"sc":15,"fv":"AT-RISK","cat":"A","rsi":75,"macd":"bull","vol":4.2,"ch":"Double Bottom","cd":"Bullish Engulfing","px":4.6,"sup":"4.2","res":"","stop":"close<3.9 (raw, tight)","tgt":"\u2153 at 4.8, trail rest","f":"Double Bottom \u00b7 candle +1.45% \u00b7 >50MA \u00b7 uptrend \u00b7 20d-breakout \u00b7 vol 4.2x \u00b7 MACD bull \u00b7 RSI 75"},{"s":"PHPMF1","t":"risk","e":"EXTENDED","p":8,"sc":16,"fv":"AT-RISK","cat":"A","rsi":67,"macd":"bull","vol":3.3,"ch":"Double Bottom","cd":"Bullish Engulfing","px":3.5,"sup":"3.3","res":"3.6","stop":"close<3.1 (raw, tight)","tgt":"\u2153 at 3.7, trail rest","f":"Double Bottom \u00b7 candle \u00b7 >50MA \u00b7 uptrend \u00b7 20d-breakout \u00b7 vol 3.3x \u00b7 MACD bull \u00b7 RSI 67"},{"s":"MEGHNAINS","t":"risk","e":"EXTENDED","p":8,"sc":10,"fv":"SUSTAINABLE","cat":"A","rsi":77,"macd":"bull","vol":2.7,"ch":"Double Bottom","cd":"Three Outside Up","px":41.5,"sup":"32.5","res":"","stop":"n/a","tgt":"\u2014","f":"Double Bottom \u00b7 candle \u00b7 >50MA \u00b7 uptrend \u00b7 20d-breakout \u00b7 vol 2.7x \u00b7 MACD bull \u00b7 RSI 77"},{"s":"ZAHINTEX","t":"risk","e":"IN-ZONE","p":7,"sc":0,"fv":"AT-RISK","cat":"Z","rsi":52,"macd":"bull","vol":2.3,"ch":"Double Bottom","cd":"","px":8.8,"sup":"8.7","res":"8.9","stop":"close<8.8 (raw, tight)","tgt":"\u2153 at 11.2, trail rest","f":"Double Bottom \u00b7 >50MA \u00b7 uptrend \u00b7 vol 2.3x \u00b7 MACD bull \u00b7 RSI 52"},{"s":"IFILISLMF1","t":"risk","e":"EXTENDED","p":7,"sc":19,"fv":"AT-RISK","cat":"A","rsi":75,"macd":"bull","vol":6.2,"ch":"Inverse Head & Shoulders","cd":"Bullish Engulfing","px":5.0,"sup":"3.9","res":"","stop":"if held: EXIT now / close<4.3","tgt":"\u2014","f":"Inverse Head & Shoulders \u00b7 >50MA \u00b7 uptrend \u00b7 20d-breakout \u00b7 vol 6.2x \u00b7 MACD bull \u00b7 RSI 75"},{"s":"TRUSTB1MF","t":"risk","e":"EXTENDED","p":7,"sc":0,"fv":"AT-RISK","cat":"A","rsi":67,"macd":"bull","vol":4.9,"ch":"Ascending Triangle","cd":"Bullish Marubozu","px":3.5,"sup":"3.3","res":"3.6","stop":"if held: EXIT now / close<3.1","tgt":"\u2014","f":"Ascending Triangle \u00b7 >50MA \u00b7 uptrend \u00b7 20d-breakout \u00b7 vol 4.9x \u00b7 MACD bull \u00b7 RSI 67"},{"s":"GREENDELMF","t":"risk","e":"EXTENDED","p":7,"sc":18,"fv":"AT-RISK","cat":"A","rsi":76,"macd":"bull","vol":4.3,"ch":"Inverse Head & Shoulders","cd":"Bullish Marubozu","px":4.3,"sup":"3.9","res":"","stop":"if held: EXIT now / close<3.6","tgt":"\u2014","f":"Inverse Head & Shoulders \u00b7 >50MA \u00b7 uptrend \u00b7 20d-breakout \u00b7 vol 4.3x \u00b7 MACD bull \u00b7 RSI 76"},{"s":"1JANATAMF","t":"risk","e":"EXTENDED","p":7,"sc":10,"fv":"AT-RISK","cat":"A","rsi":80,"macd":"bull","vol":4.2,"ch":"Double Bottom","cd":"","px":3.6,"sup":"3.2","res":"","stop":"n/a","tgt":"\u2014","f":"Double Bottom \u00b7 >50MA \u00b7 uptrend \u00b7 20d-breakout \u00b7 vol 4.2x \u00b7 MACD bull \u00b7 RSI 80"},{"s":"AIBL1STIMF","t":"risk","e":"EXTENDED","p":7,"sc":11,"fv":"AT-RISK","cat":"A","rsi":86,"macd":"bull","vol":4.2,"ch":"Double Bottom","cd":"","px":5.8,"sup":"4.1","res":"","stop":"if held: EXIT now / close<4.3","tgt":"\u2014","f":"Double Bottom \u00b7 >50MA \u00b7 uptrend \u00b7 20d-breakout \u00b7 vol 4.2x \u00b7 MACD bull \u00b7 RSI 86"},{"s":"EMERALDOIL","t":"risk","e":"EXTENDED","p":7,"sc":0,"fv":"AT-RISK","cat":"Z","rsi":63,"macd":"bull","vol":4.2,"ch":"Double Bottom","cd":"","px":26.8,"sup":"23.0","res":"27.0","stop":"close<23.1 (raw, tight)","tgt":"\u2153 at 40.2, trail rest","f":"Double Bottom \u00b7 >50MA \u00b7 uptrend \u00b7 vol 4.2x \u00b7 MACD bull \u00b7 RSI 63"}]}}